Metadata-Version: 1.1
Name: passdb
Version: 0.2-1
Summary: PassDB (Password DB) for shared password management using GPG
Home-page: https://github.com/raags/passdb
Author: Raghu Udiyar
Author-email: raghusiddarth@gmail.com
License: Apache 2.0
Download-URL: https://github.com/raags/passdb/tarball/0.2
Platform: UNKNOWN
Classifier: Development Status :: 4 - Beta
Classifier: Environment :: Console
Classifier: Intended Audience :: Developers
Classifier: License :: OSI Approved :: Apache Software License
Classifier: Operating System :: OS Independent
Classifier: Programming Language :: Python :: 2.6
Classifier: Programming Language :: Python :: 2.7
Classifier: Programming Language :: Python :: 3.3
Classifier: Programming Language :: Python :: 3.4
Classifier: Programming Language :: Python :: 3.5
Classifier: Topic :: Security
Classifier: Topic :: Utilities
Classifier: Topic :: System :: Distributed Computing
